{
  "document_id": "index_c6b0a214c2c7",
  "site_id": "sai_whu",
  "space_id": "sai",
  "title": "武汉大学人工智能学院",
  "source_url": "https://sai.whu.edu.cn/",
  "published_at": null,
  "content_hash": "5452884f59e198267e416f5d7805db4015288dc81ab49560e3d6590c1a1daeab",
  "markdown_path": "knowledge/sources/sai_whu/documents/index_c6b0a214c2c7/current.md",
  "raw_html_path": "knowledge/sources/sai_whu/documents/index_c6b0a214c2c7/raw.html",
  "quality": {
    "ok": true,
    "score": 1.0,
    "warnings": [],
    "metrics": {
      "chars": 417,
      "lines": 12,
      "main_nav_hits": 0,
      "footer_hits": 0,
      "breadcrumb_hits": 0,
      "script_hits": 0,
      "pagination_hits": 0,
      "duplicate_line_ratio": 0.0
    }
  }
}
